ksalf/__init__.py
ksalf/handler.py
ksalf-0.0.2.dist-info/LICENSE
ksalf-0.0.2.dist-info/METADATA
ksalf-0.0.2.dist-info/WHEEL
ksalf-0.0.2.dist-info/top_level.txt
ksalf-0.0.2.dist-info/RECORD
