Metadata-Version: 2.1
Name: ksalf
Version: 0.0.2
Summary: A lightweight webserver implementation [inspired by flask]
Home-page: https://github.com/Haegi/ksalf
Author: Benjamin Haegenlaeuer
Author-email: benni.haegenlaeuer@outlook.de
License: UNKNOWN
Platform: UNKNOWN
Classifier: Programming Language :: Python :: 3
Classifier: License :: OSI Approved :: MIT License
Classifier: Operating System :: OS Independent
Requires-Python: >=3.6
